LuTime/__init__.py
LuTime/lutime.py
LuTime-2.0.0.dist-info/METADATA
LuTime-2.0.0.dist-info/WHEEL
LuTime-2.0.0.dist-info/top_level.txt
LuTime-2.0.0.dist-info/RECORD
