Metadata-Version: 2.1
Name: LuTime
Version: 2.0.0
Summary: UNKNOWN
Home-page: UNKNOWN
License: UNKNOWN
Platform: UNKNOWN
Requires-Dist: time
Requires-Dist: datetime
